cfglog.py
cfglog-1.0.0.dist-info/licenses/LICENSE
cfglog-1.0.0.dist-info/METADATA
cfglog-1.0.0.dist-info/WHEEL
cfglog-1.0.0.dist-info/top_level.txt
cfglog-1.0.0.dist-info/RECORD
