Metadata-Version: 2.4
Name: cfglog
Version: 1.0.0
Summary: Configure Logging Easily
Home-page: http://github.com/cfglog/cfglog
Author: Zhiqing Xiao
Author-email: xzq.xiaozhiqing@gmail.com
License: MIT
Classifier: Programming Language :: Python
License-File: LICENSE
Dynamic: author
Dynamic: author-email
Dynamic: classifier
Dynamic: description
Dynamic: description-content-type
Dynamic: home-page
Dynamic: license
Dynamic: license-file
Dynamic: summary
